getpycomic/__init__.py
getpycomic/cli.py
getpycomic/controller.py
getpycomic/downloader.py
getpycomic/drivers/geckodriver
getpycomic/drivers/geckodriver.exe
getpycomic/drivers/plugins/uBlock0_1.63.3rc2.firefox.signed.xpi
getpycomic/drivers/plugins.txt
getpycomic/engines/__init__.py
getpycomic/engines/base.py
getpycomic/engines/selenium.py
getpycomic/engines/thread_selenium.py
getpycomic/errorhandlerdecorator.py
getpycomic/imagehandler.py
getpycomic/jsondata.py
getpycomic/models.py
getpycomic/pages/__init__.py
getpycomic/pages/base.py
getpycomic/pages/novelcool.py
getpycomic/pages/tmomanga.py
getpycomic/pages/zonatmo.py
getpycomic/pathclass.py
getpycomic/requests_data.py
getpycomic/sorter_volume_chapter.py
getpycomic/status.py
getpycomic/supported_webs.py
getpycomic/utils.py
getpycomic/version.py
getpycomic/ziphandler.py
getpycomic-0.1.2.dist-info/METADATA
getpycomic-0.1.2.dist-info/WHEEL
getpycomic-0.1.2.dist-info/entry_points.txt
getpycomic-0.1.2.dist-info/RECORD
