Metadata-Version: 2.3
Name: getpycomic
Version: 0.1.2
Summary: Take the manga/comics wherever you want.
License: MIT
Keywords: comic,manga,cbz,scraping,selenium
Author: kurotom
Author-email: 55354389+kurotom@users.noreply.github.com
Requires-Python: >=3.9,<4.0
Classifier: License :: OSI Approved :: MIT License
Classifier: Operating System :: OS Independent
Classifier: Programming Language :: Python :: 3
Classifier: Programming Language :: Python :: 3.9
Classifier: Programming Language :: Python :: 3.10
Classifier: Programming Language :: Python :: 3.11
Classifier: Programming Language :: Python :: 3.12
Classifier: Programming Language :: Python :: 3.13
Requires-Dist: fake-useragent (>=2.2.0,<3.0.0)
Requires-Dist: pillow (>=11.0,<12.0)
Requires-Dist: platformdirs (>=4.3.7,<5.0.0)
Requires-Dist: requests (>=2.32.3,<3.0.0)
Requires-Dist: selenium (>=4.22.0,<5.0.0)
Project-URL: Bug Tracker, https://github.com/kurotom/getpycomic/issues
Project-URL: Repository, https://github.com/kurotom/getpycomic
